MANIFEST.in
README.rst
setup.cfg
setup.py
tw2/__init__.py
tw2.tipster.egg-info/PKG-INFO
tw2.tipster.egg-info/SOURCES.txt
tw2.tipster.egg-info/dependency_links.txt
tw2.tipster.egg-info/entry_points.txt
tw2.tipster.egg-info/namespace_packages.txt
tw2.tipster.egg-info/not-zip-safe
tw2.tipster.egg-info/requires.txt
tw2.tipster.egg-info/top_level.txt
tw2/tipster/__init__.py
tw2/tipster/base.py
tw2/tipster/samples.py
tw2/tipster/widgets.py
tw2/tipster/static/css/tipster.css
tw2/tipster/static/js/tipster.js
tw2/tipster/templates/__init__.py
tw2/tipster/templates/tipster.mak