Metadata-Version: 1.1
Name: tw2.tipster
Version: 2.0b9
Summary: Tips for your website :)
Home-page: http://github.com/toscawidgets/tw2.tipster
Author: Ralph Bean
Author-email: rbean@redhat.com
License: MIT
Keywords: toscawidgets.widgets
Platform: UNKNOWN
Classifier: Development Status :: 3 - Alpha
Classifier: Environment :: Web Environment
Classifier: Environment :: Web Environment :: ToscaWidgets
Classifier: Topic :: Software Development :: Libraries :: Python Modules
Classifier: Topic :: Software Development :: Widget Sets
Classifier: Intended Audience :: Developers
Classifier: Operating System :: OS Independent
Classifier: Programming Language :: Python
